migrations/__init__.py
Arbitrium_interface-0.1.dist-info/METADATA
Arbitrium_interface-0.1.dist-info/WHEEL
Arbitrium_interface-0.1.dist-info/top_level.txt
Arbitrium_interface-0.1.dist-info/RECORD
