Metadata-Version: 2.1
Name: Arbitrium-interface
Version: 0.1
Summary: A custom Django admin interface
Home-page: UNKNOWN
Author: Arnav
License: UNKNOWN
Platform: UNKNOWN
Classifier: Development Status :: 3 - Alpha
Classifier: Framework :: Django
Classifier: Intended Audience :: Developers
Classifier: Programming Language :: Python :: 3
Classifier: Programming Language :: Python :: 3.8
Requires-Dist: Django >=3.2
Requires-Dist: django-admin-interface
